tqc/__init__.py
tqc/cli.py
tqc-0.2.4.dist-info/LICENSE
tqc-0.2.4.dist-info/METADATA
tqc-0.2.4.dist-info/WHEEL
tqc-0.2.4.dist-info/entry_points.txt
tqc-0.2.4.dist-info/top_level.txt
tqc-0.2.4.dist-info/RECORD
