Metadata-Version: 2.1
Name: tqc
Version: 0.2.4
Summary: Command line interface for the TinyQueries Compiler
Home-page: https://github.com/querytechnology/tqc-py
Author: Wouter Diesveld
Author-email: wouter@querytechnology.com
License: UNKNOWN
Platform: UNKNOWN
Classifier: Programming Language :: Python :: 3
Classifier: License :: OSI Approved :: MIT License
Classifier: Operating System :: OS Independent
License-File: LICENSE
Requires-Dist: requests
Requires-Dist: colorama
Requires-Dist: pyyaml
